newspaper_no_download/__init__.py
newspaper_no_download/api.py
newspaper_no_download/article.py
newspaper_no_download/cleaners.py
newspaper_no_download/configuration.py
newspaper_no_download/extractors.py
newspaper_no_download/images.py
newspaper_no_download/mthreading.py
newspaper_no_download/network.py
newspaper_no_download/nlp.py
newspaper_no_download/outputformatters.py
newspaper_no_download/parsers.py
newspaper_no_download/settings.py
newspaper_no_download/source.py
newspaper_no_download/text.py
newspaper_no_download/urls.py
newspaper_no_download/utils.py
newspaper_no_download/version.py
newspaper_no_download/resources/misc/google_sources.txt
newspaper_no_download/resources/misc/popular_sources.txt
newspaper_no_download/resources/misc/stopwords-nlp-en.txt
newspaper_no_download/resources/misc/useragents.txt
newspaper_no_download/resources/text/stopwords-ar.txt
newspaper_no_download/resources/text/stopwords-da.txt
newspaper_no_download/resources/text/stopwords-de.txt
newspaper_no_download/resources/text/stopwords-el.txt
newspaper_no_download/resources/text/stopwords-en.txt
newspaper_no_download/resources/text/stopwords-es.txt
newspaper_no_download/resources/text/stopwords-fi.txt
newspaper_no_download/resources/text/stopwords-fr.txt
newspaper_no_download/resources/text/stopwords-he.txt
newspaper_no_download/resources/text/stopwords-hi.txt
newspaper_no_download/resources/text/stopwords-hu.txt
newspaper_no_download/resources/text/stopwords-id.txt
newspaper_no_download/resources/text/stopwords-it.txt
newspaper_no_download/resources/text/stopwords-ko.txt
newspaper_no_download/resources/text/stopwords-mk.txt
newspaper_no_download/resources/text/stopwords-nb.txt
newspaper_no_download/resources/text/stopwords-nl.txt
newspaper_no_download/resources/text/stopwords-no.txt
newspaper_no_download/resources/text/stopwords-pl.txt
newspaper_no_download/resources/text/stopwords-pt.txt
newspaper_no_download/resources/text/stopwords-ru.txt
newspaper_no_download-0.0.1.dist-info/DESCRIPTION.rst
newspaper_no_download-0.0.1.dist-info/METADATA
newspaper_no_download-0.0.1.dist-info/RECORD
newspaper_no_download-0.0.1.dist-info/WHEEL
newspaper_no_download-0.0.1.dist-info/metadata.json
newspaper_no_download-0.0.1.dist-info/top_level.txt
