Metadata-Version: 2.0
Name: newspaper-no-download
Version: 0.0.1
Summary: Newspaper3k library with no download phase
Home-page: https://github.com/jxub/newspaper_no_download
Author: Jakub Janarek
Author-email: jjanarek@gmail.com
License: MIT
Platform: UNKNOWN
Classifier: Programming Language :: Python :: 3
Classifier: Natural Language :: English
Classifier: Intended Audience :: Developers
Requires-Dist: beautifulsoup4 (>=4.4.1)
Requires-Dist: Pillow (>=3.3.0)
Requires-Dist: PyYAML (>=3.11)
Requires-Dist: cssselect (>=0.9.2)
Requires-Dist: lxml (>=3.6.0)
Requires-Dist: nltk (>=3.2.1)
Requires-Dist: requests (>=2.10.0)
Requires-Dist: feedparser (>=5.2.1)
Requires-Dist: tldextract (>=2.0.1)
Requires-Dist: feedfinder2 (>=0.0.4)
Requires-Dist: jieba3k (>=0.35.1)
Requires-Dist: python-dateutil (>=2.5.3)
